sdwi2iextender/__init__.py
sdwi2iextender/gradio_helpers.py
sdwi2iextender/lib/img2img_component_injector.py
sdwi2iextender/lib/img2img_tab_extender.py
sdwi2iextender/lib/install_scripts.py
sdwi2iextender/lib/one_time_callable.py
sdwi2iextender/lib/operation_mode.py
sdwi2iextender-0.2.3.dist-info/LICENSE
sdwi2iextender-0.2.3.dist-info/METADATA
sdwi2iextender-0.2.3.dist-info/WHEEL
sdwi2iextender-0.2.3.dist-info/top_level.txt
sdwi2iextender-0.2.3.dist-info/RECORD
