Metadata-Version: 2.1
Name: sdwi2iextender
Version: 0.2.3
Summary: Stable Diffusion Webui Img2img Tab Extender
Author: Plads
Classifier: Programming Language :: Python :: 3
Classifier: License :: OSI Approved :: MIT License
Classifier: Operating System :: OS Independent
Requires-Python: >=3.8
License-File: LICENSE
